xenusia/NNWrappers.py
xenusia/models.py
xenusia/run_prediction.py
xenusia/utils.py
xenusia/vector_gen.py
xenusia/models/nn4_final_state_dict_contact.mtorch
xenusia/models/nn4_final_state_dict_domain.mtorch
xenusia-0.0.2.data/scripts/xenusia_standalone
xenusia-0.0.2.dist-info/LICENSE
xenusia-0.0.2.dist-info/METADATA
xenusia-0.0.2.dist-info/WHEEL
xenusia-0.0.2.dist-info/top_level.txt
xenusia-0.0.2.dist-info/RECORD
