Metadata-Version: 2.1
Name: xenusia
Version: 0.0.2
Summary: A predictor of DNA-binding proteins in archaea
Home-page: https://github.com/grogdrinker/xenusia
Author: Gabriele Orlando
Author-email: gabriele.orlando@kuleuven.be
Classifier: Programming Language :: Python :: 3
Classifier: Operating System :: OS Independent
License-File: LICENSE
Requires-Dist: torch
Requires-Dist: numpy
Requires-Dist: scikit-learn
Requires-Dist: requests
